Metadata-Version: 2.1
Name: booksnake
Version: 0.3.1
Summary: Download books from the internet and send to kindle
Home-page: https://github.com/j6k4m8/booksnake/
Author: Jordan Matelsky
Author-email: j6k4m8@gmail.com
License: Apache 2.0
Keywords: kindle,ebook,download
Platform: UNKNOWN
Classifier: Programming Language :: Python :: 3.7
Classifier: Programming Language :: Python :: 3.8
